Metadata-Version: 1.1
Name: relic
Version: 1.1.2
Summary: Maintains version information for git projects
Home-page: https://github.com/spacetelescope/relic
Author: Joseph Hunkeler
Author-email: jhunk@stsci.edu
License: BSD
Platform: UNKNOWN
Classifier: License :: OSI Approved :: BSD License
Classifier: Operating System :: OS Independent
Classifier: Programming Language :: Python
Classifier: Topic :: Software Development :: Libraries :: Python Modules
